ulidgen/cli.py
ulidgen-0.1.2.dist-info/entry_points.txt
ulidgen-0.1.2.dist-info/LICENSE
ulidgen-0.1.2.dist-info/WHEEL
ulidgen-0.1.2.dist-info/METADATA
ulidgen-0.1.2.dist-info/RECORD
