Metadata-Version: 2.1
Name: ulidgen
Version: 0.1.2
Summary: Generate ULID on the command line
Home-page: https://github.com/emnoor/ulidgen
License: MIT
Author: Enam Mijbah Noor
Author-email: enammijbahnoor@gmail.com
Requires-Python: >=3.5,<4.0
Classifier: License :: OSI Approved :: MIT License
Classifier: Programming Language :: Python :: 3
Classifier: Programming Language :: Python :: 3.10
Classifier: Programming Language :: Python :: 3.5
Classifier: Programming Language :: Python :: 3.6
Classifier: Programming Language :: Python :: 3.7
Classifier: Programming Language :: Python :: 3.8
Classifier: Programming Language :: Python :: 3.9
Requires-Dist: ulid-py (>=1.1,<2.0)
Project-URL: Repository, https://github.com/emnoor/ulidgen
